quantum_animation_toolbox/__init__.py
quantum_animation_toolbox/quera_circuit_lib.py
quantum_animation_toolbox/quera_colors.py
quantum_animation_toolbox/quera_qubit_lib.py
quantum_animation_toolbox-0.1.1.dist-info/METADATA
quantum_animation_toolbox-0.1.1.dist-info/WHEEL
quantum_animation_toolbox-0.1.1.dist-info/licenses/LICENSE
quantum_animation_toolbox-0.1.1.dist-info/RECORD
