Metadata-Version: 2.4
Name: quantum-animation-toolbox
Version: 0.1.1
Summary: Manim-powered animations for visualizing quantum circuits and neutral atom moves in QuEra's hardware
License-File: LICENSE
Requires-Python: >=3.10
Requires-Dist: audioop-lts; python_version >= '3.13'
Requires-Dist: manimgl>=1.7.2
Requires-Dist: manimpango>=0.6.0
